{
    "spider": "",
    "wallpaper": "",
    "warningText": "资源来自网络，所有内容仅供学习使用，请勿用于违法及商业用途。",
    "sites": [
        {
            "key": "js_电影先生",
            "name": "电影先生",
            "type": 3,
            "api": "./js/drpy2.min.js",
            "searchable": 1,
            "quickSearch": 1,
            "filterable": 1,
            "ext": "./libs/电影先生.js"
        },
        {
            "key": "dr_荐片",
            "name": "荐片Js",
            "type": 3,
            "api": "./js/drpy2.min.js",
            "searchable": 1,
            "playerType": 1,
            "quickSearch": 1,
            "filterable": 1,
            "ext": "./libs/荐片.js"
        },
        {
            "key": "js_czsapp",
            "name": "厂长Js",
            "type": 3,
            "api": "./js/drpy2.min.js",
            "searchable": 1,
            "quickSearch": 1,
            "filterable": 1,
            "ext": "./libs/czspp.js"
        },
        {
            "key": "js_大师兄",
            "name": "大师兄影视",
            "type": 3,
            "api": "./js/drpy2.min.js",
            "searchable": 1,
            "quickSearch": 1,
            "filterable": 1,
            "ext": "./libs/大师兄影视.js"
        }
    ],
    "parses": [
        {
            "name": "Json聚合",
            "type": 3,
            "url": "Demo"
        },
        {
            "name": "Web聚合",
            "type": 3,
            "url": "Web"
        },
        {
            "name": "虾米",
            "type": 0,
            "url": "https://jx.xmflv.com/?url=",
            "ext": {
                "flag": [
                    "qq",
                    "腾讯",
                    "qiyi",
                    "爱奇艺",
                    "奇艺",
                    "youku",
                    "优酷",
                    "sohu",
                    "搜狐",
                    "letv",
                    "乐视",
                    "mgtv",
                    "芒果",
                    "imgo",
                    "rx",
                    "ltnb",
                    "bilibili",
                    "1905",
                    "xigua"
                ]
            }
        },
        {
            "name": "咸鱼",
            "type": 0,
            "url": "https://jx.xyflv.cc/?url=",
            "ext": {
                "header": {
                    "user-agent": "Mozilla/5.0(Linux;Android13;V2049ABuild/TP1A.220624.014;wv)AppleWebKit/537.36(KHTML,likeGecko)Version/4.0Chrome/116.0.0.0MobileSafari/537.36",
                    "referer": "https://www.xyflv.cc/"
                }
            }
        },
        {
            "name": "云解析",
            "type": 0,
            "url": "https://jx.yparse.com/index.php?url=",
            "ext": {
                "header": {
                    "user-agent": "Mozilla/5.0(Linux;Android13;V2049ABuild/TP1A.220624.014;wv)AppleWebKit/537.36(KHTML,likeGecko)Version/4.0Chrome/116.0.0.0MobileSafari/537.36"
                }
            }
        },
        {
            "name": "爱豆",
            "type": 0,
            "url": "https://jx.aidouer.net/?url=",
            "ext": {
                "header": {
                    "user-agent": "Mozilla/5.0(Linux;Android13;V2049ABuild/TP1A.220624.014;wv)AppleWebKit/537.36(KHTML,likeGecko)Version/4.0Chrome/116.0.0.0MobileSafari/537.36",
                    "referer": "https://jiejie.uk/"
                }
            }
        }
    ],
    "doh": [
        
    ],
    "rules": [
        
    ],
    "lives": [
        {
            "name": "直播一",
            "type": 0,
            "url": "https://izzx.cn/tv/tvzb.txt",
            "playerType": 1,
            "ua": "okhttp/3.15",
            "epg": "http://epg.112114.xyz/?ch={name}&date={date}",
            "logo": "https://epg.112114.xyz/logo/{name}.png"
        },
        {
            "name": "直播二",
            "type": 0,
            "url": "https://xhdwc.tk/tvlive.txt",
            "playerType": 1,
            "ua": "okhttp/3.15",
            "epg": "http://epg.112114.xyz/?ch={name}&date={date}",
            "logo": "https://epg.112114.xyz/logo/{name}.png"
        }
    ]
}